lc_sqlalchemy_dbutils/__init__.py
lc_sqlalchemy_dbutils/manager.py
lc_sqlalchemy_dbutils/schema.py
lc_sqlalchemy_dbutils/view.py
tests/__init__.py
tests/common.py
lc_sqlalchemy_dbutils-0.1.0.dist-info/LICENSE
lc_sqlalchemy_dbutils-0.1.0.dist-info/METADATA
lc_sqlalchemy_dbutils-0.1.0.dist-info/WHEEL
lc_sqlalchemy_dbutils-0.1.0.dist-info/top_level.txt
lc_sqlalchemy_dbutils-0.1.0.dist-info/RECORD
