Metadata-Version: 2.1
Name: lc-sqlalchemy-dbutils
Version: 0.1.0
Summary: UNKNOWN
Home-page: https://github.com/libcommon/sqlalchemy-dbutils-py
Author: libcommon
Author-email: libcommon@protonmail.com
License: UNKNOWN
Project-URL: Issue Tracker, https://github.com/libcommon/sqlalchemy-dbutils-py/issues
Project-URL: Releases, https://github.com/libcommon/sqlalchemy-dbutils-py/releases
Platform: UNKNOWN
Classifier: Intended Audience :: Developers
Classifier: Programming Language :: Python :: 3
Classifier: License :: OSI Approved :: MIT License
Classifier: Operating System :: OS Independent
Requires-Python: >=3.6
Requires-Dist: sqlalchemy (>=1.3)
